sdk_42946c74_f393_4856_9a84_41c4a80cba69/dynbatch/__init__.py
sdk_42946c74_f393_4856_9a84_41c4a80cba69/dynbatch/base.py
sdk_42946c74_f393_4856_9a84_41c4a80cba69/dynbatch/batch.py
sdk_42946c74_f393_4856_9a84_41c4a80cba69/rlog/__init__.py
sdk_42946c74_f393_4856_9a84_41c4a80cba69/rlog/eventhub.py
sdk_42946c74_f393_4856_9a84_41c4a80cba69/rlog/log.py
sdk_42946c74_f393_4856_9a84_41c4a80cba69/rlog/logimp.py
sdk_42946c74_f393_4856_9a84_41c4a80cba69-0.1.0.dist-info/WHEEL
sdk_42946c74_f393_4856_9a84_41c4a80cba69-0.1.0.dist-info/METADATA
sdk_42946c74_f393_4856_9a84_41c4a80cba69-0.1.0.dist-info/RECORD
